Workbook
Name aporte: APP!$D$12
Name patrimonio: APP!$D$15
Name qtdAnos: APP!$D$13
Name rendimentoCarteira: APP!$D$7
Name salario: APP!$D$6
Name taxaMensal: APP!$D$14

Sheet APP
B5: Configurações
B6: Salário | D6: 2000
B7: Rendimento Carteira | D7: 0.0089
B8: Sugestão de Investimento (30%) | D8: =salario*30% -> 600
B11: Investimento Mensal
B12: Quanto Investir por mês? | D12: 200
B13: Por quandos Anos? | D13: 5
B14: Taxa de Rendimento Mensal? | D14: 0.01079
B15: Patrimônio acumulado? | D15: =FV(taxaMensal,qtdAnos*12,aporte*-1) -> 16755.383
B16: Dividendos Mensais? | D16: =patrimonio*rendimentoCarteira -> 149.12291
B19: Cenários | D19: Dividendo
A20: 2 | B20: Quanto em 2 Anos? | C20: =FV(taxaMensal,$A20*12,aporte*-1) -> 5445.5255 | D20: =C20*rendimentoCarteira -> 48.465177
A21: 5 | B21: Quanto em 5 Anos? | C21: =FV(taxaMensal,$A21*12,aporte*-1) -> 16755.383 | D21: =C21*rendimentoCarteira -> 149.12291
A22: 10 | B22: Quanto em 10 Anos? | C22: =FV(taxaMensal,$A22*12,aporte*-1) -> 48656.843 | D22: =C22*rendimentoCarteira -> 433.0459
A23: 20 | B23: Quanto em 20 Anos? | C23: =FV(taxaMensal,$A23*12,aporte*-1) -> 225039.68 | D23: =C23*rendimentoCarteira -> 2002.8532
A24: 30 | B24: Qunato em 30 Anos? | C24: =FV(taxaMensal,$A24*12,aporte*-1) -> 864433.93 | D24: =C24*rendimentoCarteira -> 7693.462
B27: PERFIL | C27: Agressivo
B28: VALOR A SER INVESTIDO POR MÊS | C28: =aporte -> 200
B30: TIPO DE FII | C30: Percentual Sugerido | D30: Valores
B31: PAPEL | C31: =VLOOKUP($C$27&" - "&B31,Planilha2!A3:D21,4,FALSE) -> 0.5 | D31: =C31*$C$28 -> 100
B32: TIJOLO | C32: =VLOOKUP($C$27&" - "&B32,Planilha2!A4:D22,4,FALSE) -> 0.1 | D32: =C32*$C$28 -> 20
B33: HÍBRIDO | C33: =VLOOKUP($C$27&" - "&B33,Planilha2!A5:D23,4,FALSE) -> 0.05 | D33: =C33*$C$28 -> 10
B34: FOFs | C34: =VLOOKUP($C$27&" - "&B34,Planilha2!A6:D24,4,FALSE) -> 0.05 | D34: =C34*$C$28 -> 10
B35: DESENVOLVIMENTO | C35: =VLOOKUP($C$27&" - "&B35,Planilha2!A7:D25,4,FALSE) -> 0.2 | D35: =C35*$C$28 -> 40
B36: HOTELARIAS | C36: =VLOOKUP($C$27&" - "&B36,Planilha2!A8:D26,4,FALSE) -> 0.1 | D36: =C36*$C$28 -> 20
D37: =SUM(D31:D36) -> 200

Sheet Planilha2
A3: CHAVE | B3: PERFIL | C3: TIPO DE FII | D3: %
A4: =B4&" - "&C4 -> Convervador - PAPEL | B4: Convervador | C4: PAPEL | D4: 0.3
A5: =B5&" - "&C5 -> Convervador - TIJOLO | B5: Convervador | C5: TIJOLO | D5: 0.5
A6: =B6&" - "&C6 -> Convervador - HÍBRIDO | B6: Convervador | C6: HÍBRIDO | D6: 0.1
A7: =B7&" - "&C7 -> Convervador - FOFs | B7: Convervador | C7: FOFs | D7: 0.1
A8: =B8&" - "&C8 -> Convervador - DESENVOLVIMENTO | B8: Convervador | C8: DESENVOLVIMENTO | D8: 0
A9: =B9&" - "&C9 -> Convervador - HOTELARIAS | B9: Convervador | C9: HOTELARIAS | D9: 0
A10: =B10&" - "&C10 -> Moderado - PAPEL | B10: Moderado | C10: PAPEL | D10: 0.32
A11: =B11&" - "&C11 -> Moderado - TIJOLO | B11: Moderado | C11: TIJOLO | D11: 0.35
A12: =B12&" - "&C12 -> Moderado - HÍBRIDO | B12: Moderado | C12: HÍBRIDO | D12: 0.08
A13: =B13&" - "&C13 -> Moderado - FOFs | B13: Moderado | C13: FOFs | D13: 0.05
A14: =B14&" - "&C14 -> Moderado - DESENVOLVIMENTO | B14: Moderado | C14: DESENVOLVIMENTO | D14: 0.1
A15: =B15&" - "&C15 -> Moderado - HOTELARIAS | B15: Moderado | C15: HOTELARIAS | D15: 0.1
... A21: =B21&" - "&C21 -> Agressivo - HOTELARIAS | B21: Agressivo | C21: HOTELARIAS | D21: 0.1
